{
  "videoName": "table_12",
  "detector": "YOLOv11-nano-pose",
  "modelPath": "D:\\Desktop\\TT_Coach_AI\\yolo_table_keypoints_predict\\best.pt",
  "videoWidth": 1280,
  "videoHeight": 720,
  "exportTimestamp": 1775384518069,
  "detection": {
    "frameIndex": 125,
    "confidence": 0.9061,
    "keypoints": [
      {
        "x": 0.719782,
        "y": 0.464126,
        "confidence": 0.9051
      },
      {
        "x": 0.709018,
        "y": 0.645241,
        "confidence": 0.9852
      },
      {
        "x": 0.032417,
        "y": 0.546269,
        "confidence": 0.9418
      },
      {
        "x": 0.037309,
        "y": 0.398471,
        "confidence": 0.9024
      },
      {
        "x": 0.358545,
        "y": 0.400941,
        "confidence": 0.994
      },
      {
        "x": 0.243737,
        "y": 0.582189,
        "confidence": 0.9989
      }
    ],
    "bbox": {
      "x1": 0.044885,
      "y1": 0.353708,
      "x2": 0.759071,
      "y2": 0.618436
    },
    "keypoints_averaged": [
      {
        "x": 0.717858,
        "y": 0.465357,
        "confidence": 0.9026
      },
      {
        "x": 0.704329,
        "y": 0.644581,
        "confidence": 0.9843
      },
      {
        "x": 0.034932,
        "y": 0.54494,
        "confidence": 0.9401
      },
      {
        "x": 0.037577,
        "y": 0.398429,
        "confidence": 0.9003
      },
      {
        "x": 0.35814,
        "y": 0.401283,
        "confidence": 0.9935
      },
      {
        "x": 0.241121,
        "y": 0.581458,
        "confidence": 0.9988
      }
    ],
    "num_samples": 3
  }
}